README.md
setup.py
snn/__init__.py
snn.egg-info/PKG-INFO
snn.egg-info/SOURCES.txt
snn.egg-info/dependency_links.txt
snn.egg-info/not-zip-safe
snn.egg-info/requires.txt
snn.egg-info/top_level.txt