Metadata-Version: 1.0
Name: snn
Version: 0.4
Summary: Simple neural network for solving problems of classification and regression
Home-page: https://github.com/hpc0/simple-neural-network
Author: Herman Paul Chávez
Author-email: hpc__@outlook.com
License: BSD 2-Clause License
Platform: UNKNOWN
